llps/__init__.py
llps/cli.py
llps/constants.py
llps/exceptions.py
llps/file_types.py
llps/project_schema.py
llps/utils.py
llps/bio/__init__.py
llps/bio/bio.py
llps/bio/cli.py
llps/bio/utils.py
llps-0.5.3.dist-info/METADATA
llps-0.5.3.dist-info/RECORD
llps-0.5.3.dist-info/WHEEL
llps-0.5.3.dist-info/entry_points.txt
llps-0.5.3.dist-info/top_level.txt
tests/__init__.py
tests/test_llps.py
